chunked_uploads/__init__.py
chunked_uploads/admin.py
chunked_uploads/apps.py
chunked_uploads/constants.py
chunked_uploads/exceptions.py
chunked_uploads/models.py
chunked_uploads/response.py
chunked_uploads/serializers.py
chunked_uploads/settings.py
chunked_uploads/tests.py
chunked_uploads/views.py
uploads/__init__.py
uploads/admin.py
uploads/apps.py
uploads/constants.py
uploads/exceptions.py
uploads/models.py
uploads/response.py
uploads/serializers.py
uploads/settings.py
uploads/tests.py
uploads/views.py
chunked_uploads_attentive-1.0.0.dist-info/METADATA
chunked_uploads_attentive-1.0.0.dist-info/WHEEL
chunked_uploads_attentive-1.0.0.dist-info/top_level.txt
chunked_uploads_attentive-1.0.0.dist-info/RECORD
