Metadata-Version: 2.1
Name: chunked-uploads-attentive
Version: 1.0.0
Summary: Chunked Upload of files on gcs using Django
Author: Ayion
Author-email: <ayan@attentive.ai>
License: MIT
Keywords: python,file,transfer,chunk,chunks,upload
Classifier: Intended Audience :: Developers
Classifier: Programming Language :: Python :: 3
Classifier: Operating System :: Unix
Classifier: Operating System :: MacOS :: MacOS X
Classifier: Operating System :: Microsoft :: Windows
Requires-Dist: django
Requires-Dist: djangorestframework
Requires-Dist: google
Requires-Dist: google-cloud-storage
